taskstack/__init__.py
taskstack/__version__.py
taskstack/core.py
taskstack-0.0.1.dist-info/LICENSE
taskstack-0.0.1.dist-info/METADATA
taskstack-0.0.1.dist-info/WHEEL
taskstack-0.0.1.dist-info/top_level.txt
taskstack-0.0.1.dist-info/RECORD
