Metadata-Version: 2.1
Name: taskstack
Version: 0.0.1
Summary: 自动识别脚本字段,直接运行或修改内容执行任务
Home-page: https://www.viaviavi.org
Author: 不怕雷的雨
Author-email: viaviavi365@gmail.com
License: AGPL
Platform: UNKNOWN
Classifier: Intended Audience :: Developers
Classifier: Natural Language :: Chinese (Simplified)
Classifier: Programming Language :: Python
Classifier: Programming Language :: Python :: 3
Classifier: Programming Language :: Python :: 3.8
Classifier: Programming Language :: Python :: 3.9
Classifier: Programming Language :: Python :: 3.10
Classifier: Programming Language :: Python :: Implementation :: CPython
Classifier: Programming Language :: Python :: Implementation :: PyPy
Classifier: Topic :: Software Development :: Libraries
Requires-Python: >=3.8.0
License-File: LICENSE
Requires-Dist: certifi
Requires-Dist: chardet
Requires-Dist: charset-normalizer
Requires-Dist: cquest
Requires-Dist: idna
Requires-Dist: jsonpath
Requires-Dist: PyYAML
Requires-Dist: requests
Requires-Dist: urllib3
Requires-Dist: pyside6
